<?xml version="1.0" encoding="UTF-8"?>
<simpleviewerGallery maxImageWidth="900" maxImageHeight="900" textColor="0xcccccc" frameColor="0xffffff" frameWidth="20" stagePadding="40" thumbnailColumns="3" thumbnailRows="5" navPosition="left" title="&lt;font&gt; &lt;a href=&quot;../../galleri.html&quot;&gt;TILBAKE TIL GALLERI&lt;/a&gt; &lt;/font&gt; &lt;font size=&quot;20&quot;&gt;
Etappe 5:&lt;br&gt;Fauske (Sulitjelma) - L&#248;nsdal&lt;/font&gt;" enableRightClickOpen="false" backgroundImagePath="" imagePath="" thumbPath="">

<image>
	<filename>CIMG3425.jpg</filename>
</image>
<image>
	<filename>CIMG3428.jpg</filename>
</image>
<image>
	<filename>CIMG3430.jpg</filename>
</image>
<image>
	<filename>CIMG3431.jpg</filename>
</image>
<image>
	<filename>CIMG3436.jpg</filename>
</image>
<image>
	<filename>CIMG3437.jpg</filename>
</image>
<image>
	<filename>CIMG3440.jpg</filename>
</image>
<image>
	<filename>CIMG3441.jpg</filename>
</image>
<image>
	<filename>CIMG3442.jpg</filename>
</image>
<image>
	<filename>CIMG3445.jpg</filename>
</image>
<image>
	<filename>CIMG3446.jpg</filename>
</image>
<image>
	<filename>CIMG3452.jpg</filename>
</image>
<image>
	<filename>CIMG3453.jpg</filename>
</image>
<image>
	<filename>CIMG3454.jpg</filename>
</image>
<image>
	<filename>CIMG3456.jpg</filename>
</image>
<image>
	<filename>CIMG3460.jpg</filename>
</image>
<image>
	<filename>DSCF8457.jpg</filename>
</image>
<image>
	<filename>DSCF8458.jpg</filename>
</image>
<image>
	<filename>CIMG3468.jpg</filename>
</image>
<image>
	<filename>DSCF8460.jpg</filename>
</image>
<image>
	<filename>CIMG3471.jpg</filename>
</image>
<image>
	<filename>CIMG3475.jpg</filename>
</image>
<image>
	<filename>CIMG3476.jpg</filename>
</image>
<image>
	<filename>CIMG3482.jpg</filename>
</image>
<image>
	<filename>CIMG3485.jpg</filename>
</image>
<image>
	<filename>CIMG3486.jpg</filename>
</image>
<image>
	<filename>CIMG3487.jpg</filename>
</image>
<image>
	<filename>DSCF8464.jpg</filename>
</image>
<image>
	<filename>DSCF8466.jpg</filename>
</image>
<image>
	<filename>CIMG3491.jpg</filename>
</image>
<image>
	<filename>CIMG3493.jpg</filename>
</image>
<image>
	<filename>CIMG3495.jpg</filename>
</image>
<image>
	<filename>CIMG3503.jpg</filename>
</image>
<image>
	<filename>CIMG3507.jpg</filename>
</image>
<image>
	<filename>CIMG3508.jpg</filename>
</image>
<image>
	<filename>DSCF8471.jpg</filename>
</image>
<image>
	<filename>CIMG3511.jpg</filename>
</image>
<image>
	<filename>CIMG3513.jpg</filename>
</image>
<image>
	<filename>CIMG3514.jpg</filename>
</image>
<image>
	<filename>CIMG3516.jpg</filename>
</image>
<image>
	<filename>CIMG3518.jpg</filename>
</image>
<image>
	<filename>CIMG3530.jpg</filename>
</image>
<image>
	<filename>CIMG3532.jpg</filename>
</image>
<image>
	<filename>CIMG3535.jpg</filename>
</image>
<image>
	<filename>CIMG3539.jpg</filename>
</image>
<image>
	<filename>CIMG3546.jpg</filename>
</image>
<image>
	<filename>DSCF8474.jpg</filename>
</image>
<image>
	<filename>DSCF8477.jpg</filename>
</image>
<image>
	<filename>DSCF8481.jpg</filename>
</image>
<image>
	<filename>DSCF8484.jpg</filename>
</image>
<image>
	<filename>DSCF8485.jpg</filename>
</image>
<image>
	<filename>DSCF8486.jpg</filename>
</image>
<image>
	<filename>DSCF8487.jpg</filename>
</image>
<image>
	<filename>DSCF8488.jpg</filename>
</image>
<image>
	<filename>DSCF8489.jpg</filename>
</image>
<image>
	<filename>CIMG3562.jpg</filename>
</image>
<image>
	<filename>CIMG3564.jpg</filename>
</image>
<image>
	<filename>CIMG3565.jpg</filename>
</image>
<image>
	<filename>CIMG3566.jpg</filename>
</image>
<image>
	<filename>CIMG3567.jpg</filename>
</image>
<image>
	<filename>CIMG3572.jpg</filename>
</image>
<image>
	<filename>CIMG3573.jpg</filename>
</image>
<image>
	<filename>CIMG3574.jpg</filename>
</image>
<image>
	<filename>CIMG3588.jpg</filename>
</image>
<image>
	<filename>CIMG3589.jpg</filename>
</image>
<image>
	<filename>CIMG3591.jpg</filename>
</image>
<image>
	<filename>DSCF8499.jpg</filename>
</image>
<image>
	<filename>CIMG3603.jpg</filename>
</image>
<image>
	<filename>CIMG3605.jpg</filename>
</image>
<image>
	<filename>CIMG3606.jpg</filename>
</image>
<image>
	<filename>CIMG3615.jpg</filename>
</image>
<image>
	<filename>DSCF8500.jpg</filename>
</image>
<image>
	<filename>DSCF8501.jpg</filename>
</image>
<image>
	<filename>CIMG3618.jpg</filename>
</image>
<image>
	<filename>CIMG3632.jpg</filename>
</image>
<image>
	<filename>DSCF8511.jpg</filename>
</image>
<image>
	<filename>DSCF8512.jpg</filename>
</image>
<image>
	<filename>DSCF8513.jpg</filename>
</image>
<image>
	<filename>DSCF8514.jpg</filename>
</image>
<image>
	<filename>DSCF8518.jpg</filename>
</image>
<image>
	<filename>DSCF8520.jpg</filename>
</image>
<image>
	<filename>CIMG3635.jpg</filename>
</image>
<image>
	<filename>CIMG3642.jpg</filename>
</image>
<image>
	<filename>CIMG3648.jpg</filename>
</image>
<image>
	<filename>DSCF8523.jpg</filename>
</image>
<image>
	<filename>DSCF8524.jpg</filename>
</image>
<image>
	<filename>CIMG3666.jpg</filename>
</image>
<image>
	<filename>CIMG3683.jpg</filename>
</image>
<image>
	<filename>DSCF8527.jpg</filename>
</image>
<image>
	<filename>DSCF8532.jpg</filename>
</image>
<image>
	<filename>DSCF8542.jpg</filename>
</image>
<image>
	<filename>DSCF8543.jpg</filename>
</image>
<image>
	<filename>CIMG3684.jpg</filename>
</image>
<image>
	<filename>CIMG3689.jpg</filename>
</image>
</simpleviewerGallery>